meta_ae/__init__.py
meta_ae/action_items.py
meta_ae/admin/__init__.py
meta_ae/admin/ae_followup_admin.py
meta_ae/admin/ae_initial_admin.py
meta_ae/admin/ae_local_review_admin.py
meta_ae/admin/ae_sponsor_review_admin.py
meta_ae/admin/ae_susar_admin.py
meta_ae/admin/ae_tmg_admin.py
meta_ae/admin/death_report_admin.py
meta_ae/admin/death_report_tmg_admin.py
meta_ae/admin/death_report_tmg_second_admin.py
meta_ae/admin/hospitalization_admin.py
meta_ae/admin/modeladmin_mixins.py
meta_ae/admin_site.py
meta_ae/apps.py
meta_ae/baker_recipes.py
meta_ae/choices.py
meta_ae/constants.py
meta_ae/forms/__init__.py
meta_ae/forms/ae_followup_form.py
meta_ae/forms/ae_initial_form.py
meta_ae/forms/ae_local_review_form.py
meta_ae/forms/ae_sponsor_review_form.py
meta_ae/forms/ae_susar_form.py
meta_ae/forms/ae_tmg_form.py
meta_ae/forms/death_report_form.py
meta_ae/forms/death_report_tmg_form.py
meta_ae/forms/death_report_tmg_second_form.py
meta_ae/forms/hospitalization_form.py
meta_ae/forms/modelform_mixins.py
meta_ae/list_data.py
meta_ae/migrations/0001_initial.py
meta_ae/migrations/0002_auto_20191024_1000.py
meta_ae/migrations/0003_auto_20191102_0033.py
meta_ae/migrations/0004_auto_20191114_0821.py
meta_ae/migrations/0005_auto_20210624_0225.py
meta_ae/migrations/0006_aelocalreview_aesponsorreview.py
meta_ae/migrations/0007_auto_20210911_2036.py
meta_ae/migrations/0008_auto_20211011_1657.py
meta_ae/migrations/0009_auto_20220307_1929.py
meta_ae/migrations/0010_auto_20220704_1841.py
meta_ae/migrations/0011_alter_aefollowup_action_identifier_and_more.py
meta_ae/migrations/0012_auto_20220826_0258.py
meta_ae/migrations/0013_auto_20220826_0322.py
meta_ae/migrations/0014_auto_20220826_0406.py
meta_ae/migrations/0015_auto_20220907_0157.py
meta_ae/migrations/0016_rename_narrative_aetmg_investigator_narrative_and_more.py
meta_ae/migrations/0017_auto_20221130_2257.py
meta_ae/migrations/0018_alter_deathreporttmg_cause_of_death_agreed_and_more.py
meta_edc-1.6.15.dist-info/licenses/LICENSE
meta_edc-1.6.15.dist-info/WHEEL
meta_edc-1.6.15.dist-info/METADATA
meta_edc-1.6.15.dist-info/RECORD
