Metadata-Version: 2.4
Name: meta-edc
Version: 1.6.15
Summary: META Trial EDC (https://www.isrctn.com/ISRCTN76157257)
Keywords: django,clinicedc,META EDC,EDC,clinical trials,META Trial,ISRCTN76157257
Author: Erik van Widenfelt, Jonathan Willitts
Author-email: Erik van Widenfelt <ew2789@gmail.com>, Jonathan Willitts <j.willitts@ucl.ac.uk>
License-Expression: GPL-3.0-or-later
License-File: LICENSE
Classifier: Environment :: Web Environment
Classifier: Framework :: Django
Classifier: Framework :: Django :: 5.2
Classifier: Framework :: Django :: 6.0
Classifier: Intended Audience :: Developers
Classifier: Intended Audience :: Science/Research
Classifier: Operating System :: OS Independent
Classifier: Programming Language :: Python :: 3.12
Classifier: Programming Language :: Python :: 3.13
Requires-Dist: django==5.2.10
Requires-Dist: celery>=5.6.2
Requires-Dist: clinicedc==2.4.6
Requires-Dist: edc-he>=1.5.2
Requires-Dist: edc-microscopy>=1.4.2
Requires-Dist: edc-mnsi>=1.4.0
Requires-Dist: edc-phq9>=1.3.1
Requires-Dist: edc-qol>=1.4.0
Requires-Dist: notebook>=7.4.7
Requires-Python: >=3.12, <3.14
